ADR/Analysis/Aerodynamics/AerodynamicPlots.py
ADR/Analysis/Aerodynamics/__init__.py
ADR/Analysis/Performance/Power.py
ADR/Analysis/Performance/Takeoff.py
ADR/Analysis/Performance/__init__.py
ADR/Analysis/Performance/run_Power.py
ADR/Analysis/Performance/run_Takeoff.py
ADR/Analysis/Performance/tests/__init__.py
ADR/Analysis/Performance/tests/test_Power.py
ADR/Analysis/Performance/tests/test_Takeoff.py
ADR/Analysis/Stability/FlightStability/FlightStability.py
ADR/Analysis/Stability/FlightStability/__init__.py
ADR/Analysis/Stability/FlightStability/run_FlightStability.py
ADR/Analysis/Stability/FlightStability/tests/__init__.py
ADR/Analysis/Stability/FlightStability/tests/test_FlightStability.py
ADR/Analysis/Stability/__init__.py
ADR/Analysis/__init__.py
ADR/Checkers/Dimensions.py
ADR/Checkers/Scoreboard.py
ADR/Checkers/StaticMargin.py
ADR/Checkers/TrimmRange.py
ADR/Checkers/__init__.py
ADR/Checkers/tests/test_Dimensions.py
ADR/Checkers/tests/test_Scoreboard.py
ADR/Checkers/tests/test_StaticMargin.py
ADR/Checkers/tests/test_TrimmRange.py
ADR/Components/Aerodynamic_components/Aerodynamic_section.py
ADR/Components/Aerodynamic_components/Aerodynamic_surface.py
ADR/Components/Aerodynamic_components/Airfoil.py
ADR/Components/Aerodynamic_components/HS.py
ADR/Components/Aerodynamic_components/VS.py
ADR/Components/Aerodynamic_components/Wing.py
ADR/Components/Aerodynamic_components/__init__.py
ADR/Components/Aerodynamic_components/tests/__init__ .py
ADR/Components/Aerodynamic_components/tests/test_Aerodynamic_section.py
ADR/Components/Aerodynamic_components/tests/test_Aerodynamic_surface.py
ADR/Components/Aerodynamic_components/tests/test_Airfoil.py
ADR/Components/Aerodynamic_components/tests/test_HS.py
ADR/Components/Aerodynamic_components/tests/test_Moment_on_CG.py
ADR/Components/Aerodynamic_components/tests/test_VS.py
ADR/Components/Aerodynamic_components/tests/test_Wing.py
ADR/Components/Component.py
ADR/Components/Plane.py
ADR/Components/Points/CA.py
adr.ca-1.0.dist-info/LICENSE
adr.ca-1.0.dist-info/WHEEL
adr.ca-1.0.dist-info/METADATA
adr.ca-1.0.dist-info/RECORD
